LICENSE
MANIFEST.in
README.md
pyproject.toml
setup.cfg
setup.py
lib/sinsy/src/COPYING
lib/sinsy/src/README
lib/sinsy/src/bin/sinsy.cpp
lib/sinsy/src/include/sinsy/ILabelOutput.h
lib/sinsy/src/include/sinsy/LabelStrings.h
lib/sinsy/src/include/sinsy/sinsy.h
lib/sinsy/src/lib/Sinsy.cpp
lib/sinsy/src/lib/converter/ConfGroup.cpp
lib/sinsy/src/lib/converter/ConfGroup.h
lib/sinsy/src/lib/converter/ConfManager.cpp
lib/sinsy/src/lib/converter/ConfManager.h
lib/sinsy/src/lib/converter/Converter.cpp
lib/sinsy/src/lib/converter/Converter.h
lib/sinsy/src/lib/converter/IConf.h
lib/sinsy/src/lib/converter/IConvertable.h
lib/sinsy/src/lib/converter/PhonemeInfo.cpp
lib/sinsy/src/lib/converter/PhonemeInfo.h
lib/sinsy/src/lib/converter/UnknownConf.cpp
lib/sinsy/src/lib/converter/UnknownConf.h
lib/sinsy/src/lib/converter/util_converter.cpp
lib/sinsy/src/lib/converter/util_converter.h
lib/sinsy/src/lib/hts_engine_API/HtsEngine.cpp
lib/sinsy/src/lib/hts_engine_API/HtsEngine.h
lib/sinsy/src/lib/hts_engine_API/SynthConditionImpl.cpp
lib/sinsy/src/lib/hts_engine_API/SynthConditionImpl.h
lib/sinsy/src/lib/hts_engine_API/hts_engine/src/COPYING
lib/sinsy/src/lib/hts_engine_API/hts_engine/src/README
lib/sinsy/src/lib/hts_engine_API/hts_engine/src/bin/hts_engine.c
lib/sinsy/src/lib/hts_engine_API/hts_engine/src/include/HTS_engine.h
lib/sinsy/src/lib/hts_engine_API/hts_engine/src/lib/HTS_audio.c
lib/sinsy/src/lib/hts_engine_API/hts_engine/src/lib/HTS_engine.c
lib/sinsy/src/lib/hts_engine_API/hts_engine/src/lib/HTS_gstream.c
lib/sinsy/src/lib/hts_engine_API/hts_engine/src/lib/HTS_hidden.h
lib/sinsy/src/lib/hts_engine_API/hts_engine/src/lib/HTS_label.c
lib/sinsy/src/lib/hts_engine_API/hts_engine/src/lib/HTS_misc.c
lib/sinsy/src/lib/hts_engine_API/hts_engine/src/lib/HTS_model.c
lib/sinsy/src/lib/hts_engine_API/hts_engine/src/lib/HTS_pstream.c
lib/sinsy/src/lib/hts_engine_API/hts_engine/src/lib/HTS_sstream.c
lib/sinsy/src/lib/hts_engine_API/hts_engine/src/lib/HTS_vocoder.c
pysinsy.egg-info/PKG-INFO
pysinsy.egg-info/SOURCES.txt
pysinsy.egg-info/dependency_links.txt
pysinsy.egg-info/requires.txt
pysinsy.egg-info/top_level.txt
