Metadata-Version: 2.1
Name: pysinsy
Version: 0.0.5
Summary: A python wrapper for sinsy
Home-page: https://github.com/r9y9/pysinsy
Author: Ryuichi Yamamoto
Author-email: zryuichi@gmail.com
License: MIT
Keywords: Sinsy,Research
Classifier: Operating System :: POSIX
Classifier: Operating System :: Unix
Classifier: Operating System :: MacOS
Classifier: Programming Language :: Cython
Classifier: Programming Language :: Python
Classifier: Programming Language :: Python :: 3
Classifier: Programming Language :: Python :: 3.7
Classifier: Programming Language :: Python :: 3.8
Classifier: Programming Language :: Python :: 3.9
Classifier: License :: OSI Approved :: MIT License
Classifier: Topic :: Scientific/Engineering
Classifier: Topic :: Software Development
Classifier: Intended Audience :: Science/Research
Classifier: Intended Audience :: Developers
Provides-Extra: docs
Provides-Extra: lint
Provides-Extra: test
License-File: LICENSE
